pikaQ/__init__.py
pikaQ/_modidx.py
pikaQ/functions.py
pikaQ/queries.py
pikaQ/terms.py
pikaQ/utils.py
pikaQ-1.0.2.dist-info/LICENSE
pikaQ-1.0.2.dist-info/METADATA
pikaQ-1.0.2.dist-info/WHEEL
pikaQ-1.0.2.dist-info/entry_points.txt
pikaQ-1.0.2.dist-info/top_level.txt
pikaQ-1.0.2.dist-info/RECORD
