Metadata-Version: 2.1
Name: pikaQ
Version: 1.0.2
Summary: Programmatically generate SQL queries for different database platforms.
Home-page: https://github.com/feynlee/pikaQ
Author: Ziyue Li
Author-email: liziyue241@gmail.com
License: Apache Software License 2.0
Keywords: nbdev jupyter notebook python
Classifier: Development Status :: 4 - Beta
Classifier: Intended Audience :: Developers
Classifier: Natural Language :: English
Classifier: Programming Language :: Python :: 3.8
Classifier: Programming Language :: Python :: 3.9
Classifier: Programming Language :: Python :: 3.10
Classifier: License :: OSI Approved :: Apache Software License
Requires-Python: >=3.8
License-File: LICENSE
Requires-Dist: fastcore
Provides-Extra: dev
Requires-Dist: nbdev ; extra == 'dev'
Requires-Dist: jupyter ; extra == 'dev'
